[ 
    {
        "from": "John Lennon",
        "to": "Bill O'Reilly",
        "type": "battle",
        "label": ""
    }, {
        "from": "John Lennon",
        "to": "George Bush",
        "type": "mention-doesnt-exist",
        "label": "I wonder how much George Bush paid you to suck his dick"
    }, {
        "from": "Bill O'Reilly",
        "to": "Paul McCartney",
        "type": "mention-doesnt-exist",
        "label": "You're Paul McCartney's bitch, with less talent than Ringo"
    }, {
        "from": "Bill O'Reilly",
        "to": "Ringo",
        "type": "mention-doesnt-exist",
        "label": "You're Paul McCartney's bitch, with less talent than Ringo"
    }, {
        "from": "Bill O'Reilly",
        "to": "Yoko Ono",
        "type": "mention-doesnt-exist",
        "label": "And I'd rather suck George Bush's dick than Yoko Ono's"
    }, {
        "from": "Bill O'Reilly",
        "to": "Don Cheadle",
        "type": "mention-doesnt-exist",
        "label": "Cause I'm evil, heart blacker than Don Cheadle"
    }, {
        "from": "Darth Vader",
        "to": "Adolf Hitler",
        "type": "battle",
        "label": ""
    }, {
        "from": "Adolf Hitler",
        "to": "Rick Moranis",
        "type": "mention-doesnt-exist",
        "label": " I preferred you in Spaceballs-the Rick Moranis version!"
    }, {
        "from": "Darth Vader",
        "to": "Napoleon Bonaparte",
        "type": "mention-didnt-exist",
        "label": "You're a pissed off little prick with a Napoleon dick"
    }, {
        "from": "Abe Lincoln",
        "to": "Chuck Norris",
        "type": "battle",
        "label": ""
    }, {
        "from": "Chuck Norris",
        "to": "John Wilkes Booth",
        "type": "mention-doesnt-exist",
        "label": "My raps will blow your mind like a verbal John Wilkes Booth"
    }, {
        "from": "Abe Lincoln",
        "to": "John McCain",
        "type": "mention-doesnt-exist",
        "label": "I've got my face on the side of a mountain, you voted for John McCain"
    }, {
        "from": "Sarah Palin",
        "to": "Lady Gaga",
        "type": "battle",
        "label": ""
    }, {
        "from": "Lady Gaga",
        "to": "Michael Jackson",
        "type": "mention-didnt-exist",
        "label": "With the most dysfunctional family since the Jackson fucking Five"
    }, {
        "from": "Sarah Palin",
        "to": "Madonna",
        "type": "mention-doesnt-exist",
        "label": "Everything you do is just a rerun of Madonna"
    }, {
        "from": "Lady Gaga",
        "to": "John McCain",
        "type": "mention-doesnt-exist",
        "label": " History will regret you like John McCain"
    }, {
        "from": "Hulk Hogan",
        "to": "Kim Jong-Il",
        "type": "battle",
        "label": ""
    }, {
        "from": "Hulk Hogan",
        "to": "Macho Man",
        "type": "battle",
        "label": ""
    }, {
        "from": "Kim Jong-Il",
        "to": "Macho Man",
        "type": "battle",
        "label": ""
    }, {
        "from": "Kim Jong-Il",
        "to": "Ric Flair",
        "type": "mention-doesnt-exist",
        "label": "I'm coming at you like the Asian Ric Flair"
    }, {
        "from": "Kim Jong-Il",
        "to": "Barbie",
        "type": "mention-doesnt-exist",
        "label": "Your whole fam's a bunch of Barbies, dude"
    }, {
        "from": "Hulk Hogan",
        "to": "Sonic the Hedgehog",
        "type": "mention-doesnt-exist",
        "label": "You look like Sonic the Hedgehog's mother"
    }, {
        "from": "Hulk Hogan",
        "to": "South Park",
        "type": "mention-doesnt-exist",
        "label": "I'll hang you from the ropes like South Park puppet show"
    }, {
        "from": "Justin Bieber",
        "to": "Beethoven",
        "type": "battle",
        "label": ""
    }, {
        "from": "Justin Bieber",
        "to": "Chewbacca",
        "type": "mention-doesnt-exist",
        "label": "Man it looks like Chewbacca wiped his ass on your head"
    }, {
        "from": "Justin Bieber",
        "to": "Michael Jackson",
        "type": "mention-didnt-exist",
        "label": "I'm the next Michael Jackson, you smell like Betty White"
    }, {
        "from": "Justin Bieber",
        "to": "Betty White",
        "type": "mention-doesnt-exist",
        "label": "I'm the next Michael Jackson, you smell like Betty White"
    }, {
        "from": "Beethoven",
        "to": "Bach",
        "type": "mention-doesnt-exist",
        "label": "Ask Bach, I got more cock than Smith and Wesson"
    }, {
        "from": "Justin Bieber",
        "to": "Kim Kardashian",
        "type": "mention-doesnt-exist",
        "label": "I got Kim Kardashian in my bed backstage"
    }, {
        "from": "Beethoven",
        "to": "Usher",
        "type": "mention-doesnt-exist",
        "label": "You wanna be a little white Usher? Here, show them their seats!"
    }, {
        "from": "Albert Einstein",
        "to": "Stephen Hawking",
        "type": "battle",
        "label": ""
    }, {
        "from": "Albert Einstein",
        "to": "Wall-E",
        "type": "mention-doesnt-exist",
        "label": "You sound like WALL-E having sex with a Speak & Spell"
    }, {
        "from": "Stephen Hawking",
        "to": "Moses",
        "type": "mention-actor",
        "label": "I'm the Snoop Dogg of Science"
    }, {
        "from": "Stephen Hawking",
        "to": "Carl Sagan",
        "type": "mention-doesnt-exist",
        "label": "I'm about to bake raps from scratch like Carl Sagan"
    }, {
        "from": "Genghis Khan",
        "to": "The Easter Bunny",
        "type": "battle",
        "label": ""
    }, {
        "from": "Genghis Khan",
        "to": "Kahn",
        "type": "mention-doesnt-exist",
        "label": "Your bunny ass about to feel the wrath of Kahn"
    }, {
        "from": "The Easter Bunny",
        "to": "Jesus",
        "type": "mention-doesnt-exist",
        "label": "We should keep it peaceful, homeboy, Jesus!"
    }, {
        "from": "Napoleon Bonaparte",
        "to": "Napoleon Dynamite",
        "type": "battle",
        "label": ""
    }, {
        "from": "Napoleon Dynamite",
        "to": "Horatio Nelson",
        "type": "mention-doesnt-exist",
        "label": "I got skills I'll put you in a half Horatio Nelson"
    }, {
        "from": "Napoleon Dynamite",
        "to": "Boris Yeltsin",
        "type": "mention-doesnt-exist",
        "label": "You're the ugliest thing that's ever failed in Russia since Boris Yeltsin"
    }, {
        "from": "Billy Mays",
        "to": "Ben Franklin",
        "type": "battle",
        "label": ""
    }, {
        "from": "Billy Mays",
        "to": "The ShamWow Guy",
        "type": "battle",
        "label": ""
    }, {
        "from": "Ben Franklin",
        "to": "The ShamWow Guy",
        "type": "battle",
        "label": ""
    }, {
        "from": "Ben Franklin",
        "to": "Rick James",
        "type": "mention-doesnt-exist",
        "label": "You couldn't sell Rick James a bag of crack, you're out of practice"
    }, {
        "from": "Ben Franklin",
        "to": "Arthur Miller",
        "type": "mention-doesnt-exist",
        "label": " Call me Arthur Miller son, cause it's death of a salesman"
    }, {
        "from": "Gandalf",
        "to": "Dumbledore",
        "type": "battle",
        "label": ""
    }, {
        "from": "Dr Seuss",
        "to": "William Shakespeare",
        "type": "battle",
        "label": ""
    }, {
        "from": "William Shakespeare",
        "to": "Stephanie Meyer",
        "type": "mention-implicit",
        "label": "I bet you wrote The Twilight books too!"
    }, {
        "from": "William Shakespeare",
        "to": "John Lennon",
        "type": "mention-implicit",
        "label": "I'm switching up my style like the Beatles with my pieces"
    }, {
        "from": "William Shakespeare",
        "to": "Jim Henson",
        "type": "mention-implicit",
        "label": "You think your new book might include a trisyllabic meter and some ghetto Muppet creatures"
    }, {
        "from": "Mr. T",
        "to": "Mr. Rogers",
        "type": "battle",
        "label": ""
    }, {
        "from": "Mr. T",
        "to": "Bill Cosby",
        "type": "mention-didnt-exist",
        "label": "Bill Cosby wants his sweater"
    }, {
        "from": "Mr. T",
        "to": "Bill Cosby",
        "type": "mention-didnt-exist",
        "label": "Bill Cosby wants his sweater"
    }, {
        "from": "Captain Kirk",
        "to": "Christopher Columbus",
        "type": "battle",
        "label": ""
    }, {
        "from": "Christopher Columbus",
        "to": "Khan",
        "type": "mention-doesnt-exist",
        "label": "My rhymes will burrow in your ears like The Wrath of Khan"
    }, {
        "from": "Christopher Columbus",
        "to": "Isabela I",
        "type": "mention-doesnt-exist",
        "label": "We'll see how Isabella likes my Captain's log"
    }, {
        "from": "Christopher Columbus",
        "to": "Sulu",
        "type": "mention-doesnt-exist",
        "label": " I've got a neck chop for Spock I'll put my sword through Sulu"
    }, {
        "from": "Christopher Columbus",
        "to": "Spock",
        "type": "mention-doesnt-exist",
        "label": " I've got a neck chop for Spock I'll put my sword through Sulu"
    }, {
        "from": "Nice Peter",
        "to": "Epiclloyd",
        "type": "battle",
        "label": ""
    }, {
        "from": "Epiclloyd",
        "to": "Bill O'Reilly",
        "type": "mention",
        "label": "You and Bill O'Reilly can both suck my dick!"
    }, {
        "from": "Nice Peter",
        "to": "Chuck Norris",
        "type": "mention",
        "label": "You've got as much music talent as Chuck fucking Norris"
    }, {
        "from": "Nice Peter",
        "to": "Gollum",
        "type": "mention-didnt-exist",
        "label": "It's like I'm battle rapping a fat version of Gollum"
    }, {
        "from": "Epiclloyd",
        "to": "KassemG",
        "type": "mention-doesnt-exist",
        "label": "You were nothing before you rode up on KassemG's jock"
    }, {
        "from": "Hitler",
        "to": "Vader 2",
        "type": "battle",
        "label": ""
    }, {
        "from": "Vader 2",
        "to": "Hitler",
        "type": "battle",
        "label": ""
    }, {
        "from": "Master Chief",
        "to": "Leonidas",
        "type": "battle",
        "label": ""
    }, {
        "from": "Leonidas",
        "to": "Master Chief",
        "type": "battle",
        "label": ""
    }, {
        "from": "Mario Bros.",
        "to": "Wright Bros.",
        "type": "battle",
        "label": ""
    }, {
        "from": "Wright Bros.",
        "to": "Mario Bros.",
        "type": "battle",
        "label": ""
    }, {
        "from": "Michael Jackson",
        "to": "Elvis Presley",
        "type": "battle",
        "label": ""
    }, {
        "from": "Elvis Presley",
        "to": "Michael Jackson",
        "type": "battle",
        "label": ""
    }, {
        "from": "Cleopatra",
        "to": "Marilyn Monroe",
        "type": "battle",
        "label": ""
    }, {
        "from": "Marilyn Monroe",
        "to": "Cleopatra",
        "type": "battle",
        "label": ""
    }, {
        "from": "Steve Jobs",
        "to": "Bill Gates",
        "type": "battle",
        "label": ""
    }, {
        "from": "Bill Gates",
        "to": "Steve Jobs",
        "type": "battle",
        "label": ""
    }, {
        "from": "Frank Sinatra",
        "to": "Freddie Mercury",
        "type": "battle",
        "label": ""
    }, {
        "from": "Freddie Mercury",
        "to": "Frank Sinatra",
        "type": "battle",
        "label": ""
    }, {
        "from": "Barack Obama",
        "to": "Mitt Romney",
        "type": "battle",
        "label": ""
    }, {
        "from": "Mitt Romney",
        "to": "Barack Obama",
        "type": "battle",
        "label": ""
    }, {
        "from": "Doc Brown",
        "to": "Doctor Who",
        "type": "battle",
        "label": ""
    }, {
        "from": "Doctor Who",
        "to": "Doc Brown",
        "type": "battle",
        "label": ""
    }, {
        "from": "Bruce Lee",
        "to": "Clint Eastwood",
        "type": "battle",
        "label": ""
    }, {
        "from": "Clint Eastwood",
        "to": "Bruce Lee",
        "type": "battle",
        "label": ""
    }, {
        "from": "Batman",
        "to": "Sherlock Holmes",
        "type": "battle",
        "label": ""
    }, {
        "from": "Sherlock Holmes",
        "to": "Batman",
        "type": "battle",
        "label": ""
    }, {
        "from": "Moses",
        "to": "Santa Claus",
        "type": "battle",
        "label": ""
    }, {
        "from": "Santa Claus",
        "to": "Moses",
        "type": "battle",
        "label": ""
    }, {
        "to": "Eve",
        "from": "Adam",
        "type": "battle",
        "label": ""
    }, {
        "from": "Eve",
        "to": "Adam",
        "type": "battle",
        "label": ""
    }, {
        "from": "Gandhi",
        "to": "Martin Luther King Jr.",
        "type": "battle",
        "label": ""
    }, {
        "from": "Martin Luther King Jr.",
        "to": "Gandhi",
        "type": "battle",
        "label": ""
    }, {
        "from": "Nikola Tesla",
        "to": "Thomas Edison",
        "type": "battle",
        "label": ""
    }, {
        "from": "Thomas Edison",
        "to": "Nikola Tesla",
        "type": "battle",
        "label": ""
    }, {
        "from": "Babe Ruth",
        "to": "Lance Armstrong",
        "type": "battle",
        "label": ""
    }, {
        "from": "Lance Armstrong",
        "to": "Babe Ruth",
        "type": "battle",
        "label": ""
    }, {
        "from": "Mozart",
        "to": "Skrillex",
        "type": "battle",
        "label": ""
    }, {
        "from": "Skrillex",
        "to": "Mozart",
        "type": "battle",
        "label": ""
    }, {
        "from": "Rasputin",
        "to": "Stalin",
        "type": "battle",
        "label": ""
    }, {
        "from": "Stalin",
        "to": "Rasputin",
        "type": "battle",
        "label": ""
    }, {
        "from": "Darth Vader",
        "to": "Adolf Hitler 3",
        "type": "battle",
        "label": ""
    }, {
        "from": "Adolf Hitler 3",
        "to": "Darth Vader",
        "type": "battle",
        "label": ""
    }, {
        "from": "Blackbeard",
        "to": "Al Capone",
        "type": "battle",
        "label": ""
    }, {
        "from": "Al Capone",
        "to": "Blackbeard",
        "type": "battle",
        "label": ""
    }, {
        "from": "Miley Cyrus",
        "to": "Joan Of Arc",
        "type": "battle",
        "label": ""
    }, {
        "from": "Joan Of Arc",
        "to": "Miley Cyrus",
        "type": "battle",
        "label": ""
    }, {
        "from": "Bob Ross",
        "to": "Pablo Picasso",
        "type": "battle",
        "label": ""
    }, {
        "from": "Pablo Picasso",
        "to": "Bob Ross",
        "type": "battle",
        "label": ""
    }, {
        "from": "Michael Jordan",
        "to": "Muhammad Ali",
        "type": "battle",
        "label": ""
    }, {
        "from": "Muhammad Ali",
        "to": "Michael Jordan",
        "type": "battle",
        "label": ""
    }, {
        "from": "Donald Trump",
        "to": "Ebenezer Scrooge",
        "type": "battle",
        "label": ""
    }, {
        "from": "Ebenezer Scrooge",
        "to": "Donald Trump",
        "type": "battle",
        "label": ""
    }, {
        "from": "Rick Grimes",
        "to": "Walter White",
        "type": "battle",
        "label": ""
    }, {
        "from": "Walter White",
        "to": "Rick Grimes",
        "type": "battle",
        "label": ""
    }, {
        "from": "Goku",
        "to": " Superman",
        "type": "battle",
        "label": ""
    }, {
        "from": " Superman",
        "to": "Goku",
        "type": "battle",
        "label": ""
    }, {
        "from": "Stephen King",
        "to": "Edgar Allan Poe",
        "type": "battle",
        "label": ""
    }, {
        "from": "Edgar Allan Poe",
        "to": "Stephen King",
        "type": "battle",
        "label": ""
    }, {
        "from": "Sir Isaac Newton",
        "to": "Bill Nye",
        "type": "battle",
        "label": ""
    }, {
        "from": "Bill Nye",
        "to": "Sir Isaac Newton",
        "type": "battle",
        "label": ""
    }, {
        "from": "George Washington",
        "to": "William Wallace",
        "type": "battle",
        "label": ""
    }, {
        "from": "William Wallace",
        "to": "George Washington",
        "type": "battle",
        "label": ""
    }, {
        "to": "TMNT",
        "from": "Artists",
        "type": "battle",
        "label": ""
    }, {
        "from": "TMNT",
        "to": "Artists",
        "type": "battle",
        "label": ""
    }, {
        "from": "Ghostbusters",
        "to": "Mythbusters",
        "type": "battle",
        "label": ""
    }, {
        "from": "Mythbusters",
        "to": "Ghostbusters",
        "type": "battle",
        "label": ""
    }, {
        "from": "Romeo And Juliet",
        "to": "Bonnie And Clyde",
        "type": "battle",
        "label": ""
    }, {
        "from": "Bonnie And Clyde",
        "to": "Romeo And Juliet",
        "type": "battle",
        "label": ""
    }, {
        "to": "Thor",
        "from": "Zeus",
        "type": "battle",
        "label": ""
    }, {
        "from": "Thor",
        "to": "Zeus",
        "type": "battle",
        "label": ""
    }, {
        "from": "Jack The Ripper",
        "to": "Hannibal Lecter",
        "type": "battle",
        "label": ""
    }, {
        "from": "Hannibal Lecter",
        "to": "Jack The Ripper",
        "type": "battle",
        "label": ""
    }, {
        "to": "Ellen",
        "from": "Oprah",
        "type": "battle",
        "label": ""
    }, {
        "from": "Ellen",
        "to": "Oprah",
        "type": "battle",
        "label": ""
    }, {
        "from": "Steven Spielberg",
        "to": "Alfred Hitchcock",
        "type": "battle",
        "label": ""
    }, {
        "from": "Alfred Hitchcock",
        "to": "Steven Spielberg",
        "type": "battle",
        "label": ""
    }, {
        "from": "Lewis And Clark",
        "to": "Bill And Ted",
        "type": "battle",
        "label": ""
    }, {
        "from": "Bill And Ted",
        "to": "Lewis And Clark",
        "type": "battle",
        "label": ""
    }, {
        "from": "David Copperfield",
        "to": "Harry Houdini",
        "type": "battle",
        "label": ""
    }, {
        "from": "Harry Houdini",
        "to": "David Copperfield",
        "type": "battle",
        "label": ""
    }, {
        "from": "Terminator",
        "to": "Robocop",
        "type": "battle",
        "label": ""
    }, {
        "from": "Robocop",
        "to": "Terminator",
        "type": "battle",
        "label": ""
    }, {
        "from": "Eastern Philosophers",
        "to": "Western Philosophers",
        "type": "battle",
        "label": ""
    }, {
        "from": "Western Philosophers",
        "to": "Eastern Philosophers",
        "type": "battle",
        "label": ""
    }, {
        "from": "Shaka Zulu",
        "to": "Julius Caesar",
        "type": "battle",
        "label": ""
    }, {
        "from": "Julius Caesar",
        "to": "Shaka Zulu",
        "type": "battle",
        "label": ""
    }, {
        "from": "Jim Henson",
        "to": "Stan Lee",
        "type": "battle",
        "label": ""
    }, {
        "from": "Stan Lee",
        "to": "Jim Henson",
        "type": "battle",
        "label": ""
    }, {
        "from": "J. R. R. Tolkien",
        "to": "George R. R. Martin",
        "type": "battle",
        "label": ""
    }, {
        "from": "George R. R. Martin",
        "to": "J. R. R. Tolkien",
        "type": "battle",
        "label": ""
    }, {
        "from": "Gordon Ramsay",
        "to": "Julia Child",
        "type": "battle",
        "label": ""
    }, {
        "from": "Julia Child",
        "to": "Gordon Ramsay",
        "type": "battle",
        "label": ""
    }, {
        "from": "Frederick Douglass",
        "to": "Thomas Jefferson",
        "type": "battle",
        "label": ""
    }, {
        "from": "Thomas Jefferson",
        "to": "Frederick Douglass",
        "type": "battle",
        "label": ""
    }, {
        "from": "James Bond",
        "to": "Austin Powers",
        "type": "battle",
        "label": ""
    }, {
        "from": "Austin Powers",
        "to": "James Bond",
        "type": "battle",
        "label": ""
    }, {
        "from": "Bruce Banner",
        "to": "Bruce Jenner",
        "type": "battle",
        "label": ""
    }, {
        "from": "Bruce Jenner",
        "to": "Bruce Banner",
        "type": "battle",
        "label": ""
    }, {
        "from": "Alexander the Great",
        "to": "Ivan the Terrible",
        "type": "battle",
        "label": ""
    }, {
        "from": "Ivan the Terrible",
        "to": "Alexander the Great",
        "type": "battle",
        "label": ""
    }, {
        "from": "Donald Trump",
        "to": "Hillary Clinton",
        "type": "battle",
        "label": ""
    }, {
        "from": "Hillary Clinton",
        "to": "Donald Trump",
        "type": "battle",
        "label": ""
    }, {
        "from": "Ash Ketchum",
        "to": "Charles Darwin",
        "type": "battle",
        "label": ""
    }, {
        "from": "Charles Darwin",
        "to": "Ash Ketchum",
        "type": "battle",
        "label": ""
    }, {
        "from": "Wonder Woman",
        "to": "Stevie Wonder",
        "type": "battle",
        "label": ""
    }, {
        "from": "Stevie Wonder",
        "to": "Wonder Woman",
        "type": "battle",
        "label": ""
    }, {
        "from": "Tony Hawk",
        "to": "Wayne Gretzky",
        "type": "battle",
        "label": ""
    }, {
        "from": "Wayne Gretzky",
        "to": "Tony Hawk",
        "type": "battle",
        "label": ""
    }, {
        "from": "Theodore Roosevelt",
        "to": "Winston Churchill",
        "type": "battle",
        "label": ""
    }, {
        "from": "Winston Churchill",
        "to": "Theodore Roosevelt",
        "type": "battle",
        "label": ""
    }, {
        "from": "Nice Peter",
        "to": "EpicLLOYD 2",
        "type": "battle",
        "label": ""
    }, {
        "from": "EpicLLOYD 2",
        "to": "Nice Peter",
        "type": "battle",
        "label": ""
    }, {
        "from": "Batman",
        "to": "Elon Musk",
        "type": "battle",
        "label": ""
    }, {
        "from": "Elon Musk",
        "to": "Batman",
        "type": "battle",
        "label": ""
    }, {
        "from": "Deadpool",
        "to": "Boba Fett",
        "type": "battle",
        "label": ""
    }, {
        "from": "Boba Fett",
        "to": "Deadpool",
        "type": "battle",
        "label": ""
    }, {
        "from": "Donald Trump",
        "to": "Joe Biden",
        "type": "battle",
        "label": ""
    }, {
        "from": "Joe Biden",
        "to": "Donald Trump",
        "type": "battle",
        "label": ""
    }, {
        "from": "Elon Musk",
        "to": "Mark Zuckerberg",
        "type": "battle",
        "label": ""
    }, {
        "from": "Mark Zuckerberg",
        "to": "Elon Musk",
        "type": "battle",
        "label": ""
    }, {
        "from": "George Carlin",
        "to": "Richard Pryor",
        "type": "battle",
        "label": ""
    }, {
        "from": "Richard Pryor",
        "to": "George Carlin",
        "type": "battle",
        "label": ""
    }, {
        "from": "Guy Fawkes",
        "to": "Che Guevara",
        "type": "battle",
        "label": ""
    }, {
        "from": "Che Guevara",
        "to": "Guy Fawkes",
        "type": "battle",
        "label": ""
    }, {
        "from": "Jacques Cousteau",
        "to": "Steve Irwin",
        "type": "battle",
        "label": ""
    }, {
        "from": "Steve Irwin",
        "to": "Jacques Cousteau",
        "type": "battle",
        "label": ""
    }, {
        "from": "Larry Bird",
        "to": "Big Bird",
        "type": "battle",
        "label": ""
    }, {
        "from": "Big Bird",
        "to": "Larry Bird",
        "type": "battle",
        "label": ""
    }, {
        "from": "Mother Teresa",
        "to": "Sigmund Freud",
        "type": "battle",
        "label": ""
    }, {
        "from": "Sigmund Freud",
        "to": "Mother Teresa",
        "type": "battle",
        "label": ""
    }, {
        "from": "PewDiePie",
        "to": "T-Series",
        "type": "battle",
        "label": ""
    }, {
        "from": "T-Series",
        "to": "PewDiePie",
        "type": "battle",
        "label": ""
    }, {
        "from": "Ronald McDonald",
        "to": "The Burger King",
        "type": "battle",
        "label": ""
    }, {
        "from": "The Burger King",
        "to": "Ronald McDonald",
        "type": "battle",
        "label": ""
    }, {
        "from": "Thanos",
        "to": "J. Robert Oppenheimer",
        "type": "battle",
        "label": ""
    }, {
        "from": "J. Robert Oppenheimer",
        "to": "Thanos",
        "type": "battle",
        "label": ""
    }, {
        "from": "The Joker",
        "to": "Pennywise",
        "type": "battle",
        "label": ""
    }, {
        "from": "Pennywise",
        "to": "The Joker",
        "type": "battle",
        "label": ""
    }, {
        "from": "Vlad The Impaler",
        "to": "Count Dracula",
        "type": "battle",
        "label": ""
    }, {
        "from": "Count Dracula",
        "to": "Vlad The Impaler",
        "type": "battle",
        "label": ""
    }, {
        "from": "Wolverine",
        "to": "Freddy Krueger",
        "type": "battle",
        "label": ""
    }, {
        "from": "Freddy Krueger",
        "to": "Wolverine",
        "type": "battle",
        "label": ""
    }, {
        "from": "Vlad The Impaler",
        "to": "Count Dracula",
        "type": "battle",
        "label": ""
    }, {
        "from": "Count Dracula",
        "to": "Vlad The Impaler",
        "type": "battle",
        "label": ""
    }
]